{
  "title": "Recent posts",
  "items": [
    {
      "title": "폴리움의 key_on 파라미터와 GeoJson 및 GeoData 이해하기",
      "permalink": "/blog/features_collection"
    },
    {
      "title": "파이토치를 이용한 데이터셋 분리",
      "permalink": "/blog/bean-scope"
    },
    {
      "title": "파이토치를 이용한 데이터셋 분리",
      "permalink": "/blog/pytorch-dataset-split"
    },
    {
      "title": "스프링 부트 개발의 기초 상식",
      "permalink": "/blog/spring-boot-dev-basic"
    },
    {
      "title": "넘파이와 친해진 판다스 2.0",
      "permalink": "/blog/pandas-2-feature-1"
    }
  ]
}